LICENSE
MANIFEST.in
README.md
setup.cfg
setup.py
tap_satismeter/__init__.py
tap_satismeter.egg-info/PKG-INFO
tap_satismeter.egg-info/SOURCES.txt
tap_satismeter.egg-info/dependency_links.txt
tap_satismeter.egg-info/entry_points.txt
tap_satismeter.egg-info/requires.txt
tap_satismeter.egg-info/top_level.txt
tap_satismeter/schemas/responses.json